[{"id":"32.10.01","name":"LEMAHSUGIH"},{"id":"32.10.02","name":"BANTARUJEG"},{"id":"32.10.03","name":"CIKIJING"},{"id":"32.10.04","name":"TALAGA"},{"id":"32.10.05","name":"ARGAPURA"},{"id":"32.10.06","name":"MAJA"},{"id":"32.10.07","name":"MAJALENGKA"},{"id":"32.10.08","name":"SUKAHAJI"},{"id":"32.10.09","name":"RAJAGALUH"},{"id":"32.10.10","name":"LEUWIMUNDING"},{"id":"32.10.11","name":"JATIWANGI"},{"id":"32.10.12","name":"DAWUAN"},{"id":"32.10.13","name":"KADIPATEN"},{"id":"32.10.14","name":"KERTAJATI"},{"id":"32.10.15","name":"JATITUJUH"},{"id":"32.10.16","name":"LIGUNG"},{"id":"32.10.17","name":"SUMBERJAYA"},{"id":"32.10.18","name":"PANYINGKIRAN"},{"id":"32.10.19","name":"PALASAH"},{"id":"32.10.20","name":"CIGASONG"},{"id":"32.10.21","name":"SINDANGWANGI"},{"id":"32.10.22","name":"BANJARAN"},{"id":"32.10.23","name":"CINGAMBUL"},{"id":"32.10.24","name":"KASOKANDEL"},{"id":"32.10.25","name":"SINDANG"},{"id":"32.10.26","name":"MALAUSMA"}]