[{"id":"35.26.01","name":"BANGKALAN"},{"id":"35.26.02","name":"SOCAH"},{"id":"35.26.03","name":"BURNEH"},{"id":"35.26.04","name":"KAMAL"},{"id":"35.26.05","name":"AROSBAYA"},{"id":"35.26.06","name":"GEGER"},{"id":"35.26.07","name":"KLAMPIS"},{"id":"35.26.08","name":"SEPULU"},{"id":"35.26.09","name":"TANJUNG BUMI"},{"id":"35.26.10","name":"KOKOP"},{"id":"35.26.11","name":"KWANYAR"},{"id":"35.26.12","name":"LABANG"},{"id":"35.26.13","name":"TANAH MERAH"},{"id":"35.26.14","name":"TRAGAH"},{"id":"35.26.15","name":"BLEGA"},{"id":"35.26.16","name":"MODUNG"},{"id":"35.26.17","name":"KONANG"},{"id":"35.26.18","name":"GALIS"}]