[{"id":"95.02.01","name":"OKSIBIL"},{"id":"95.02.02","name":"KIWIROK"},{"id":"95.02.03","name":"OKBIBAB"},{"id":"95.02.04","name":"IWUR"},{"id":"95.02.05","name":"BATOM"},{"id":"95.02.06","name":"BORME"},{"id":"95.02.07","name":"KIWIROK TIMUR"},{"id":"95.02.08","name":"ABOY"},{"id":"95.02.09","name":"PEPERA"},{"id":"95.02.10","name":"BIME"},{"id":"95.02.11","name":"ALEMSOM"},{"id":"95.02.12","name":"OKBAPE"},{"id":"95.02.13","name":"KALOMDOL"},{"id":"95.02.14","name":"OKSOP"},{"id":"95.02.15","name":"SERAMBAKON"},{"id":"95.02.16","name":"OK AOM"},{"id":"95.02.17","name":"KAWOR"},{"id":"95.02.18","name":"AWINBON"},{"id":"95.02.19","name":"TARUP"},{"id":"95.02.20","name":"OKHIKA"},{"id":"95.02.21","name":"OKSAMOL"},{"id":"95.02.22","name":"OKLIP"},{"id":"95.02.23","name":"OKBEMTAU"},{"id":"95.02.24","name":"OKSEBANG"},{"id":"95.02.25","name":"OKBAB"},{"id":"95.02.26","name":"BATANI"},{"id":"95.02.27","name":"WEIME"},{"id":"95.02.28","name":"MURKIM"},{"id":"95.02.29","name":"MOFINOP"},{"id":"95.02.30","name":"JETFA"},{"id":"95.02.31","name":"TEIRAPLU"},{"id":"95.02.32","name":"EIPUMEK"},{"id":"95.02.33","name":"PAMEK"},{"id":"95.02.34","name":"NONGME"}]